pyflx/__init__.py
pyflx/pyflx.py
pyflxy/__init__.py
pyflxy/pyflx.py
pyflxy/pylogger.py
pyflxy/pyretry.py
pyflxy/pyschedule.py
pyflxy/pytime.py
pyflxy/time.py
pyflxy/util.py
pyflxy-0.4.dist-info/LICENSE
pyflxy-0.4.dist-info/METADATA
pyflxy-0.4.dist-info/WHEEL
pyflxy-0.4.dist-info/top_level.txt
pyflxy-0.4.dist-info/RECORD
